{"_default": {"1": {"id": 1, "last_name": "fabiano", "first_name": "natalia", "date_of_birth": "12/11/1982", "gender": "f", "rank": 5, "score": 0.0, "opponents": []}, "2": {"id": 2, "last_name": "fabiano", "first_name": "maria", "date_of_birth": "22/11/1986", "gender": "f", "rank": 9, "score": 0.0, "opponents": []}, "3": {"id": 3, "last_name": "fabiano", "first_name": "juan", "date_of_birth": "24/01/1980", "gender": "8", "rank": 8, "score": 0.0, "opponents": []}, "4": {"id": 4, "last_name": "faraggi", "first_name": "marcelo", "date_of_birth": "08/03/1983", "gender": "m", "rank": 7, "score": 0.0, "opponents": []}, "5": {"id": 5, "last_name": "chanquia", "first_name": "sergio", "date_of_birth": "17/03/1976", "gender": "m", "rank": 6, "score": 0.0, "opponents": []}, "6": {"id": 6, "last_name": "faraggi", "first_name": "marisa", "date_of_birth": "04/03/1976", "gender": "f", "rank": 5, "score": 0.0, "opponents": []}, "7": {"id": 7, "last_name": "fabiano", "first_name": "nestor", "date_of_birth": "12/11/1950", "gender": "m", "rank": 50, "score": 0.0, "opponents": []}, "8": {"id": 8, "last_name": "russi", "first_name": "elba", "date_of_birth": "02/03/1947", "gender": "f", "rank": 49, "score": 0.0, "opponents": []}}}